CHANGES.txt
LICENSE.ZPL
LICENSE.txt
MANIFEST.in
README.rst
setup.py
sauna/__init__.py
sauna.reload.egg-info/PKG-INFO
sauna.reload.egg-info/SOURCES.txt
sauna.reload.egg-info/dependency_links.txt
sauna.reload.egg-info/entry_points.txt
sauna.reload.egg-info/namespace_packages.txt
sauna.reload.egg-info/not-zip-safe
sauna.reload.egg-info/requires.txt
sauna.reload.egg-info/top_level.txt
sauna/reload/__init__.py
sauna/reload/adapters.py
sauna/reload/autoinclude.py
sauna/reload/autoinclude.zcml
sauna/reload/browser.py
sauna/reload/configure.zcml
sauna/reload/eventhandlers.py
sauna/reload/events.py
sauna/reload/fiveconfigure.py
sauna/reload/fiveconfigure.zcml
sauna/reload/forkloop.py
sauna/reload/interfaces.py
sauna/reload/monkeypatcher.py
sauna/reload/reloadpaths.py
sauna/reload/utils.py
sauna/reload/watcher.py
sauna/reload/plugins/__init__.py
sauna/reload/plugins/configure.zcml
sauna/reload/plugins/theming.py
sauna/reload/templates/saunareload.pt