Metadata-Version: 1.1
Name: sauna.reload
Version: 0.5.4
Summary: Instant code reloading for Plone using a fork loop
Home-page: http://github.com/collective/sauna.reload
Author: Asko Soukka
Author-email: asko.soukka@iki.fi
License: ZPL
Keywords: plone reload zope2 restart developer
Platform: UNKNOWN
Classifier: Framework :: Plone
Classifier: Programming Language :: Python
